LICENSE
MANIFEST.in
setup.py
treeeditor/__init__.py
treeeditor/admin.py
treeeditor/conf.py
treeeditor/static/.DS_Store
treeeditor/static/treeeditor/.DS_Store
treeeditor/static/treeeditor/css/fein_tree.css
treeeditor/static/treeeditor/css/style.css
treeeditor/static/treeeditor/css/smoothness/jquery-ui-1.10.4.custom.min.css
treeeditor/static/treeeditor/css/smoothness/images/animated-overlay.gif
treeeditor/static/treeeditor/css/smoothness/images/ui-bg_flat_0_aaaaaa_40x100.png
treeeditor/static/treeeditor/css/smoothness/images/ui-bg_flat_75_ffffff_40x100.png
treeeditor/static/treeeditor/css/smoothness/images/ui-bg_glass_55_fbf9ee_1x400.png
treeeditor/static/treeeditor/css/smoothness/images/ui-bg_glass_65_ffffff_1x400.png
treeeditor/static/treeeditor/css/smoothness/images/ui-bg_glass_75_dadada_1x400.png
treeeditor/static/treeeditor/css/smoothness/images/ui-bg_glass_75_e6e6e6_1x400.png
treeeditor/static/treeeditor/css/smoothness/images/ui-bg_glass_95_fef1ec_1x400.png
treeeditor/static/treeeditor/css/smoothness/images/ui-bg_highlight-soft_75_cccccc_1x100.png
treeeditor/static/treeeditor/css/smoothness/images/ui-icons_222222_256x240.png
treeeditor/static/treeeditor/css/smoothness/images/ui-icons_2e83ff_256x240.png
treeeditor/static/treeeditor/css/smoothness/images/ui-icons_454545_256x240.png
treeeditor/static/treeeditor/css/smoothness/images/ui-icons_888888_256x240.png
treeeditor/static/treeeditor/css/smoothness/images/ui-icons_cd0a0a_256x240.png
treeeditor/static/treeeditor/images/.DS_Store
treeeditor/static/treeeditor/images/arrow-move.png
treeeditor/static/treeeditor/images/disclosure-down.png
treeeditor/static/treeeditor/images/disclosure-right.png
treeeditor/static/treeeditor/images/drag_order_circle.png
treeeditor/static/treeeditor/images/nav-bg.gif
treeeditor/static/treeeditor/js/fein_tree.js
treeeditor/static/treeeditor/js/ie_compat.js
treeeditor/static/treeeditor/js/jquery-2.1.0.min.js
treeeditor/static/treeeditor/js/jquery-ui-1.10.4.custom.min.js
twentytab_treeeditor.egg-info/PKG-INFO
twentytab_treeeditor.egg-info/SOURCES.txt
twentytab_treeeditor.egg-info/dependency_links.txt
twentytab_treeeditor.egg-info/requires.txt
twentytab_treeeditor.egg-info/top_level.txt