Metadata-Version: 1.0
Name: twentytab-treeeditor
Version: 0.1
Summary: A django app that provides FeinCMS admin tree editor.
Home-page: https://github.com/20tab/twentytab-treeeditor
Author: 20tab S.r.l.
Author-email: info@20tab.com
License: MIT License
Platform: UNKNOWN
